lptlib/__init__.py
lptlib/function/__init__.py
lptlib/function/plots.py
lptlib/function/timer.py
lptlib/function/variables.py
lptlib/io/__init__.py
lptlib/io/dataio.py
lptlib/io/plot3dio.py
lptlib/streamlines/__init__.py
lptlib/streamlines/integration.py
lptlib/streamlines/interpolation.py
lptlib/streamlines/search.py
lptlib/streamlines/stochastic_model.py
lptlib/streamlines/streamlines.py
lptlib/test_cases/__init__.py
lptlib/test_cases/oblique_shock_data.py
lptlib-0.0.5a12.dist-info/LICENSE
lptlib-0.0.5a12.dist-info/METADATA
lptlib-0.0.5a12.dist-info/WHEEL
lptlib-0.0.5a12.dist-info/top_level.txt
lptlib-0.0.5a12.dist-info/RECORD
