Metadata-Version: 2.1
Name: lptlib
Version: 0.0.5a12
Summary: One-way coupled Lagrangian Particle Tracking algorithms.
Home-page: https://github.com/kalagotla/lptlib
Author: Dilip Kalagotla
Author-email: Dilip Kalagotla <dilipkalagotla@gmail.com>
License: MIT AND (Apache-2.0 OR BSD-2-Clause)
Project-URL: homepage, https://github.com/kalagotla/lptlib
Project-URL: issues, https://github.com/kalagotla/lptlib/issues
Classifier: Programming Language :: Python :: 3
Classifier: Programming Language :: Python :: 3.10
Classifier: Programming Language :: Python :: 3.11
Classifier: Programming Language :: Python :: 3.12
Classifier: Operating System :: OS Independent
Classifier: Intended Audience :: Science/Research
Classifier: Intended Audience :: Education
Classifier: Topic :: Scientific/Engineering
Requires-Python: >=3.10
License-File: LICENSE
Requires-Dist: numpy
Requires-Dist: scipy
Requires-Dist: matplotlib
Requires-Dist: pandas
Requires-Dist: seaborn
Requires-Dist: tqdm
Requires-Dist: mpi4py
Requires-Dist: scikit-learn
